odoo/addons/l10n_ro_hr_contract/README.rst
odoo/addons/l10n_ro_hr_contract/__init__.py
odoo/addons/l10n_ro_hr_contract/__manifest__.py
odoo/addons/l10n_ro_hr_contract/data/hr.insurance.type.csv
odoo/addons/l10n_ro_hr_contract/i18n/l10n_ro_hr_contract.pot
odoo/addons/l10n_ro_hr_contract/i18n/ro.po
odoo/addons/l10n_ro_hr_contract/models/__init__.py
odoo/addons/l10n_ro_hr_contract/models/hr_contract.py
odoo/addons/l10n_ro_hr_contract/security/ir.model.access.csv
odoo/addons/l10n_ro_hr_contract/static/description/icon.png
odoo/addons/l10n_ro_hr_contract/tests/__init__.py
odoo/addons/l10n_ro_hr_contract/tests/test_hr_contract.py
odoo/addons/l10n_ro_hr_contract/views/hr_contract_view.xml
odoo11_addon_l10n_ro_hr_contract-11.0.1.0.0.99.dev18.dist-info/METADATA
odoo11_addon_l10n_ro_hr_contract-11.0.1.0.0.99.dev18.dist-info/WHEEL
odoo11_addon_l10n_ro_hr_contract-11.0.1.0.0.99.dev18.dist-info/top_level.txt
odoo11_addon_l10n_ro_hr_contract-11.0.1.0.0.99.dev18.dist-info/RECORD
